MANIFEST.in
README.rst
setup.cfg
setup.py
mockstashop/__init__.py
mockstashop/api.py
mockstashop/xml/1.5/customers.xml
mockstashop/xml/1.5/error.xml
mockstashop/xml/1.5/languages.xml
mockstashop/xml/1.5/order_states.xml
mockstashop/xml/1.5/orders.xml
mockstashop/xml/1.5/products.xml
mockstashop/xml/1.5/shops.xml
mockstashop/xml/1.5/addresses/1.xml
mockstashop/xml/1.5/addresses/2.xml
mockstashop/xml/1.5/addresses/2001.xml
mockstashop/xml/1.5/addresses/2002.xml
mockstashop/xml/1.5/addresses/2003.xml
mockstashop/xml/1.5/addresses/2004.xml
mockstashop/xml/1.5/addresses/2005.xml
mockstashop/xml/1.5/addresses/2006.xml
mockstashop/xml/1.5/addresses/3.xml
mockstashop/xml/1.5/addresses/4.xml
mockstashop/xml/1.5/addresses/5.xml
mockstashop/xml/1.5/addresses/6.xml
mockstashop/xml/1.5/addresses/7.xml
mockstashop/xml/1.5/combinations/1.xml
mockstashop/xml/1.5/combinations/10.xml
mockstashop/xml/1.5/combinations/11.xml
mockstashop/xml/1.5/combinations/12.xml
mockstashop/xml/1.5/combinations/13.xml
mockstashop/xml/1.5/combinations/14.xml
mockstashop/xml/1.5/combinations/15.xml
mockstashop/xml/1.5/combinations/16.xml
mockstashop/xml/1.5/combinations/17.xml
mockstashop/xml/1.5/combinations/18.xml
mockstashop/xml/1.5/combinations/19.xml
mockstashop/xml/1.5/combinations/2.xml
mockstashop/xml/1.5/combinations/20.xml
mockstashop/xml/1.5/combinations/21.xml
mockstashop/xml/1.5/combinations/22.xml
mockstashop/xml/1.5/combinations/23.xml
mockstashop/xml/1.5/combinations/24.xml
mockstashop/xml/1.5/combinations/25.xml
mockstashop/xml/1.5/combinations/26.xml
mockstashop/xml/1.5/combinations/3.xml
mockstashop/xml/1.5/combinations/4.xml
mockstashop/xml/1.5/combinations/5.xml
mockstashop/xml/1.5/combinations/6.xml
mockstashop/xml/1.5/combinations/7.xml
mockstashop/xml/1.5/combinations/8.xml
mockstashop/xml/1.5/combinations/9.xml
mockstashop/xml/1.5/countries/110.xml
mockstashop/xml/1.5/countries/21.xml
mockstashop/xml/1.5/countries/8.xml
mockstashop/xml/1.5/currencies/1.xml
pystashop.egg-info/PKG-INFO
pystashop.egg-info/SOURCES.txt
pystashop.egg-info/dependency_links.txt
pystashop.egg-info/not-zip-safe
pystashop.egg-info/requires.txt
pystashop.egg-info/top_level.txt