Metadata-Version: 1.0
Name: pystashop
Version: 0.4
Summary: Prestashop Webservice Python API Client
Home-page: https://github.com/openlabs/pystashop/
Author: Sharoon Thomas, Openlabs Technologies
Author-email: info@openlabs.co.in
License: UNKNOWN
Platform: any
Classifier: Development Status :: 6 - Mature
Classifier: Environment :: Web Environment
Classifier: Intended Audience :: Developers
Classifier: Operating System :: OS Independent
Classifier: Programming Language :: Python
Classifier: Topic :: Internet :: WWW/HTTP :: Dynamic Content
Classifier: Topic :: Software Development :: Libraries :: Python Modules
